ubml/__init__.py
ubml/train_test.py
ubml-1.2.dist-info/METADATA
ubml-1.2.dist-info/WHEEL
ubml-1.2.dist-info/top_level.txt
ubml-1.2.dist-info/RECORD
