Metadata-Version: 2.1
Name: ubml
Version: 1.2
Summary: Automatic Machine Learning
Author: Ubaid Ahmad
Author-email: ubaidp1049@gmail.com
